{"cameraMode":{"drawMode":0,"name":"Shaded","section":"Shading Mode"},"sceneLighting":true,"audioPlay":false,"sceneViewState":{"m_AlwaysRefresh":false,"showFog":true,"showSkybox":true,"showFlares":true,"showImageEffects":true,"showParticleSystems":true,"showVisualEffectGraphs":true,"m_FxEnabled":true},"in2DMode":false,"pivot":{"x":4.66419792175293,"y":0.5893616676330566,"z":-4.196266174316406},"rotation":{"x":-0.07486152648925781,"y":0.9183733463287354,"z":-0.2104923576116562,"w":-0.3266192078590393},"size":8.411518096923829,"orthographic":false}